{"organizations": [], "uuid": "cc9d997a3ef9ae6b8fc603cc4f4699a97e585290", "thread": {"social": {"gplus": {"shares": 0}, "pinterest": {"shares": 1}, "vk": {"shares": 0}, "linkedin": {"shares": 1}, "facebook": {"likes": 2, "shares": 2, "comments": 0}, "stumbledupon": {"shares": 0}}, "site_full": "themeforest.net", "main_image": "http://0.s3.envato.com/files/215876453/preview/Ritaj-header.__large_preview.jpg", "site_section": "http://themeforest.net/feeds/new-themeforest-items.atom", "section_title": "ThemeForest new  items", "url": "https://themeforest.net/item/ritaj-multipurpose-responsive-html-5-template/18384011", "country": "US", "domain_rank": 340, "title": "RITAJ : Multi-purpose & Responsive Html 5 Template (Creative)", "performance_score": 0, "site": "themeforest.net", "participants_count": 1, "title_full": "RITAJ : Multi-purpose & Responsive Html 5 Template (Creative)", "spam_score": 0.0, "site_type": "news", "published": "2016-11-19T05:23:00.000+02:00", "replies_count": 0, "uuid": "cc9d997a3ef9ae6b8fc603cc4f4699a97e585290"}, "author": "RM4Design", "url": "https://themeforest.net/item/ritaj-multipurpose-responsive-html-5-template/18384011", "ord_in_thread": 0, "title": "RITAJ : Multi-purpose & Responsive Html 5 Template (Creative)", "locations": [], "entities": {"persons": [], "locations": [], "organizations": []}, "highlightText": "", "language": "english", "persons": [], "text": "- the tepmlate need basic knowledge about HTML and CSS to edit images , colors …etc \n- All images in the review not included in the template 1 ) HTML \nThis theme is a one page multi purpose html5 template with all sections located within the first page . it’s divided into multiple sections includong Header, Services, Team, Skills, Done Projects, Portolio, Prices, Testimonials and Contact . \nHTML Structure \n- If u like to change the content of any of thses sections , just scroll to the the sction and do the following <img class='mypic img-responsive center-block' src=\"http://placehold.it/440x440\"> \n- find the prev line and chnage placholder image with your image. \n-All images of are replaced with placeholders So, ensure to change every placeholder image with your images . \n- just upload your images to images folder in this theme and replace the placeholder with - images/yourimage.jpg or png or whatever iextention is 2 ) CSS \n- Im using alot of css files in this template so the one to target is ‘style.css’ where u can change the font , size, colors, ...etc , but keep in mind the value maybe overwritten somewhere elese so ensure to change all the values of the attribute u want . some code /* end header */ some code /* end services */ some code /* end team */ some code etc, etc \n- If you would like to edit a specific section of the site, simply find the appropriate label in the CSS file, and then scroll down until you find the appropriate style that needs to be edited. —", "external_links": [], "published": "2016-11-19T05:23:00.000+02:00", "crawled": "2016-11-19T04:06:57.611+02:00", "highlightTitle": ""}